[
    {
        "kind": "calendar#event",
        "etag": "\"3215550402582000\"",
        "id": "5mn25hgfd8j3j3l4g2116fkf3s",
        "status": "confirmed",
        "htmlLink": "https://www.google.com/calendar/event?eid=NW1uMjVoZ2ZkOGozajNsNGcyMTE2ZmtmM3MgY19ja2JpOTg5bzJ1anRjdnR1bW1jbTc1cWpxb0Bn",
        "created": "2020-12-12T12:13:21.000Z",
        "updated": "2020-12-12T12:13:21.291Z",
        "summary": "Java",
        "description": "Check",
        "creator": {
            "email": "jmohale@student.wethinkcode.co.za"
        },
        "organizer": {
            "email": "c_ckbi989o2ujtcvtummcm75qjqo@group.calendar.google.com",
            "displayName": "Fake code clinic",
            "self": true
        },
        "start": {
            "dateTime": "2020-12-15T15:30:00+02:00",
            "timeZone": "Africa/Johannesburg"
        },
        "end": {
            "dateTime": "2020-12-15T16:00:00+02:00",
            "timeZone": "Africa/Johannesburg"
        },
        "iCalUID": "5mn25hgfd8j3j3l4g2116fkf3s@google.com",
        "sequence": 0,
        "attendees": [
            {
                "email": "jmohale@student.wethinkcode.co.za",
                "responseStatus": "accepted"
            }
        ],
        "hangoutLink": "https://meet.google.com/nzo-sfoa-ouk",
        "conferenceData": {
            "createRequest": {
                "requestId": "0b9af6d87b4e4474be04daba236aa80d",
                "conferenceSolutionKey": {
                    "type": "hangoutsMeet"
                },
                "status": {
                    "statusCode": "success"
                }
            },
            "entryPoints": [
                {
                    "entryPointType": "video",
                    "uri": "https://meet.google.com/nzo-sfoa-ouk",
                    "label": "meet.google.com/nzo-sfoa-ouk"
                },
                {
                    "entryPointType": "more",
                    "uri": "https://tel.meet/nzo-sfoa-ouk?pin=7608875608767",
                    "pin": "7608875608767"
                },
                {
                    "regionCode": "US",
                    "entryPointType": "phone",
                    "uri": "tel:+1-727-223-1731",
                    "label": "+1 727-223-1731",
                    "pin": "361380868"
                }
            ],
            "conferenceSolution": {
                "key": {
                    "type": "hangoutsMeet"
                },
                "name": "Google Meet",
                "iconUri": "https://fonts.gstatic.com/s/i/productlogos/meet_2020q4/v6/web-512dp/logo_meet_2020q4_color_2x_web_512dp.png"
            },
            "conferenceId": "nzo-sfoa-ouk",
            "signature": "AGkP/s3/dvmiZjvzqPM0U7CxGBpA"
        },
        "reminders": {
            "useDefault": true
        }
    },
    {
        "kind": "calendar#event",
        "etag": "\"3215550577806000\"",
        "id": "5i2urf08fod3mbvt0it28hvl0c",
        "status": "confirmed",
        "htmlLink": "https://www.google.com/calendar/event?eid=NWkydXJmMDhmb2QzbWJ2dDBpdDI4aHZsMGMgY19ja2JpOTg5bzJ1anRjdnR1bW1jbTc1cWpxb0Bn",
        "created": "2020-12-12T12:13:18.000Z",
        "updated": "2020-12-12T12:14:48.903Z",
        "summary": "Java",
        "description": "Check",
        "creator": {
            "email": "jmohale@student.wethinkcode.co.za"
        },
        "organizer": {
            "email": "c_ckbi989o2ujtcvtummcm75qjqo@group.calendar.google.com",
            "displayName": "Fake code clinic",
            "self": true
        },
        "start": {
            "dateTime": "2020-12-15T14:30:00+02:00",
            "timeZone": "Africa/Johannesburg"
        },
        "end": {
            "dateTime": "2020-12-15T15:00:00+02:00",
            "timeZone": "Africa/Johannesburg"
        },
        "iCalUID": "5i2urf08fod3mbvt0it28hvl0c@google.com",
        "sequence": 0,
        "attendees": [
            {
                "email": "jmohale@student.wethinkcode.co.za",
                "responseStatus": "accepted"
            },
            {
                "email": "lwanelemdu3@gmail.com",
                "responseStatus": "needsAction"
            }
        ],
        "hangoutLink": "https://meet.google.com/vtq-kxdc-won",
        "conferenceData": {
            "createRequest": {
                "requestId": "0b9af6d87b4e4474be04daba236aa80d",
                "conferenceSolutionKey": {
                    "type": "hangoutsMeet"
                },
                "status": {
                    "statusCode": "success"
                }
            },
            "entryPoints": [
                {
                    "entryPointType": "video",
                    "uri": "https://meet.google.com/vtq-kxdc-won",
                    "label": "meet.google.com/vtq-kxdc-won"
                },
                {
                    "entryPointType": "more",
                    "uri": "https://tel.meet/vtq-kxdc-won?pin=4010105507525",
                    "pin": "4010105507525"
                },
                {
                    "regionCode": "US",
                    "entryPointType": "phone",
                    "uri": "tel:+1-347-590-4822",
                    "label": "+1 347-590-4822",
                    "pin": "172573415"
                }
            ],
            "conferenceSolution": {
                "key": {
                    "type": "hangoutsMeet"
                },
                "name": "Google Meet",
                "iconUri": "https://fonts.gstatic.com/s/i/productlogos/meet_2020q4/v6/web-512dp/logo_meet_2020q4_color_2x_web_512dp.png"
            },
            "conferenceId": "vtq-kxdc-won",
            "signature": "AGkP/s0o5RLz//CDZCwO9mwEXk4V"
        },
        "reminders": {
            "useDefault": true
        }
    },
    {
        "kind": "calendar#event",
        "etag": "\"3215695458736000\"",
        "id": "q2kh7vp9k40pr71kv10c5gs140",
        "status": "confirmed",
        "htmlLink": "https://www.google.com/calendar/event?eid=cTJraDd2cDlrNDBwcjcxa3YxMGM1Z3MxNDAgY19ja2JpOTg5bzJ1anRjdnR1bW1jbTc1cWpxb0Bn",
        "created": "2020-12-13T08:22:09.000Z",
        "updated": "2020-12-13T08:22:09.368Z",
        "summary": "C++",
        "description": "C++ Vectors and Generics",
        "creator": {
            "email": "jmohale@student.wethinkcode.co.za"
        },
        "organizer": {
            "email": "c_ckbi989o2ujtcvtummcm75qjqo@group.calendar.google.com",
            "displayName": "Fake code clinic",
            "self": true
        },
        "start": {
            "dateTime": "2020-12-20T14:00:00+02:00",
            "timeZone": "Africa/Johannesburg"
        },
        "end": {
            "dateTime": "2020-12-20T14:30:00+02:00",
            "timeZone": "Africa/Johannesburg"
        },
        "iCalUID": "q2kh7vp9k40pr71kv10c5gs140@google.com",
        "sequence": 0,
        "attendees": [
            {
                "email": "jmohale@student.wethinkcode.co.za",
                "responseStatus": "accepted"
            }
        ],
        "hangoutLink": "https://meet.google.com/tsq-tbpp-hwi",
        "conferenceData": {
            "createRequest": {
                "requestId": "9e47a963713b4a349182e00bd526ac9e",
                "conferenceSolutionKey": {
                    "type": "hangoutsMeet"
                },
                "status": {
                    "statusCode": "success"
                }
            },
            "entryPoints": [
                {
                    "entryPointType": "video",
                    "uri": "https://meet.google.com/tsq-tbpp-hwi",
                    "label": "meet.google.com/tsq-tbpp-hwi"
                },
                {
                    "entryPointType": "more",
                    "uri": "https://tel.meet/tsq-tbpp-hwi?pin=5543996394543",
                    "pin": "5543996394543"
                },
                {
                    "regionCode": "US",
                    "entryPointType": "phone",
                    "uri": "tel:+1-609-469-1237",
                    "label": "+1 609-469-1237",
                    "pin": "243325561"
                }
            ],
            "conferenceSolution": {
                "key": {
                    "type": "hangoutsMeet"
                },
                "name": "Google Meet",
                "iconUri": "https://fonts.gstatic.com/s/i/productlogos/meet_2020q4/v6/web-512dp/logo_meet_2020q4_color_2x_web_512dp.png"
            },
            "conferenceId": "tsq-tbpp-hwi",
            "signature": "AGkP/s0N3ArhcRNLfzMF4nSC1hgT"
        },
        "reminders": {
            "useDefault": true
        }
    },
    {
        "kind": "calendar#event",
        "etag": "\"3215695460390000\"",
        "id": "df93ch2c3c4o9uepttqsh9j73g",
        "status": "confirmed",
        "htmlLink": "https://www.google.com/calendar/event?eid=ZGY5M2NoMmMzYzRvOXVlcHR0cXNoOWo3M2cgY19ja2JpOTg5bzJ1anRjdnR1bW1jbTc1cWpxb0Bn",
        "created": "2020-12-13T08:22:10.000Z",
        "updated": "2020-12-13T08:22:10.195Z",
        "summary": "C++",
        "description": "C++ Vectors and Generics",
        "creator": {
            "email": "jmohale@student.wethinkcode.co.za"
        },
        "organizer": {
            "email": "c_ckbi989o2ujtcvtummcm75qjqo@group.calendar.google.com",
            "displayName": "Fake code clinic",
            "self": true
        },
        "start": {
            "dateTime": "2020-12-20T14:30:00+02:00",
            "timeZone": "Africa/Johannesburg"
        },
        "end": {
            "dateTime": "2020-12-20T15:00:00+02:00",
            "timeZone": "Africa/Johannesburg"
        },
        "iCalUID": "df93ch2c3c4o9uepttqsh9j73g@google.com",
        "sequence": 0,
        "attendees": [
            {
                "email": "jmohale@student.wethinkcode.co.za",
                "responseStatus": "accepted"
            }
        ],
        "hangoutLink": "https://meet.google.com/jxb-tshu-aoe",
        "conferenceData": {
            "createRequest": {
                "requestId": "9e47a963713b4a349182e00bd526ac9e",
                "conferenceSolutionKey": {
                    "type": "hangoutsMeet"
                },
                "status": {
                    "statusCode": "success"
                }
            },
            "entryPoints": [
                {
                    "entryPointType": "video",
                    "uri": "https://meet.google.com/jxb-tshu-aoe",
                    "label": "meet.google.com/jxb-tshu-aoe"
                },
                {
                    "entryPointType": "more",
                    "uri": "https://tel.meet/jxb-tshu-aoe?pin=9673683378564",
                    "pin": "9673683378564"
                },
                {
                    "regionCode": "US",
                    "entryPointType": "phone",
                    "uri": "tel:+1-929-399-7527",
                    "label": "+1 929-399-7527",
                    "pin": "616052755"
                }
            ],
            "conferenceSolution": {
                "key": {
                    "type": "hangoutsMeet"
                },
                "name": "Google Meet",
                "iconUri": "https://fonts.gstatic.com/s/i/productlogos/meet_2020q4/v6/web-512dp/logo_meet_2020q4_color_2x_web_512dp.png"
            },
            "conferenceId": "jxb-tshu-aoe",
            "signature": "AGkP/s0Ex6bWZbOxR1n/g8MmfUbn"
        },
        "reminders": {
            "useDefault": true
        }
    },
    {
        "kind": "calendar#event",
        "etag": "\"3215695461812000\"",
        "id": "isrpphuobv9av83hb4iocghhhg",
        "status": "confirmed",
        "htmlLink": "https://www.google.com/calendar/event?eid=aXNycHBodW9idjlhdjgzaGI0aW9jZ2hoaGcgY19ja2JpOTg5bzJ1anRjdnR1bW1jbTc1cWpxb0Bn",
        "created": "2020-12-13T08:22:10.000Z",
        "updated": "2020-12-13T08:22:10.906Z",
        "summary": "C++",
        "description": "C++ Vectors and Generics",
        "creator": {
            "email": "jmohale@student.wethinkcode.co.za"
        },
        "organizer": {
            "email": "c_ckbi989o2ujtcvtummcm75qjqo@group.calendar.google.com",
            "displayName": "Fake code clinic",
            "self": true
        },
        "start": {
            "dateTime": "2020-12-20T15:00:00+02:00",
            "timeZone": "Africa/Johannesburg"
        },
        "end": {
            "dateTime": "2020-12-20T15:30:00+02:00",
            "timeZone": "Africa/Johannesburg"
        },
        "iCalUID": "isrpphuobv9av83hb4iocghhhg@google.com",
        "sequence": 0,
        "attendees": [
            {
                "email": "jmohale@student.wethinkcode.co.za",
                "responseStatus": "accepted"
            }
        ],
        "hangoutLink": "https://meet.google.com/imz-tztf-yzs",
        "conferenceData": {
            "createRequest": {
                "requestId": "9e47a963713b4a349182e00bd526ac9e",
                "conferenceSolutionKey": {
                    "type": "hangoutsMeet"
                },
                "status": {
                    "statusCode": "success"
                }
            },
            "entryPoints": [
                {
                    "entryPointType": "video",
                    "uri": "https://meet.google.com/imz-tztf-yzs",
                    "label": "meet.google.com/imz-tztf-yzs"
                },
                {
                    "entryPointType": "more",
                    "uri": "https://tel.meet/imz-tztf-yzs?pin=1652703283856",
                    "pin": "1652703283856"
                },
                {
                    "regionCode": "US",
                    "entryPointType": "phone",
                    "uri": "tel:+1-615-965-4776",
                    "label": "+1 615-965-4776",
                    "pin": "735185146"
                }
            ],
            "conferenceSolution": {
                "key": {
                    "type": "hangoutsMeet"
                },
                "name": "Google Meet",
                "iconUri": "https://fonts.gstatic.com/s/i/productlogos/meet_2020q4/v6/web-512dp/logo_meet_2020q4_color_2x_web_512dp.png"
            },
            "conferenceId": "imz-tztf-yzs",
            "signature": "AGkP/s2A0XZky/h96/dCsgr3SUFw"
        },
        "reminders": {
            "useDefault": true
        }
    },
    {
        "kind": "calendar#event",
        "etag": "\"3215735066185000\"",
        "id": "caeduilha80vk7l0jense5r2vc",
        "status": "confirmed",
        "htmlLink": "https://www.google.com/calendar/event?eid=Y2FlZHVpbGhhODB2azdsMGplbnNlNXIydmMgY19ja2JpOTg5bzJ1anRjdnR1bW1jbTc1cWpxb0Bn",
        "created": "2020-12-13T08:46:48.000Z",
        "updated": "2020-12-13T14:29:24.076Z",
        "summary": "Javascript",
        "description": "Javascript for Beginners",
        "creator": {
            "email": "jmohale@student.wethinkcode.co.za"
        },
        "organizer": {
            "email": "c_ckbi989o2ujtcvtummcm75qjqo@group.calendar.google.com",
            "displayName": "Fake code clinic",
            "self": true
        },
        "start": {
            "dateTime": "2020-12-19T14:30:00+02:00",
            "timeZone": "Africa/Johannesburg"
        },
        "end": {
            "dateTime": "2020-12-19T15:00:00+02:00",
            "timeZone": "Africa/Johannesburg"
        },
        "iCalUID": "caeduilha80vk7l0jense5r2vc@google.com",
        "sequence": 0,
        "attendees": [
            {
                "email": "jmohale@student.wethinkcode.co.za",
                "responseStatus": "accepted"
            },
            {
                "email": "smabitse@student.wethinkcode.co.za",
                "responseStatus": "accepted"
            }
        ],
        "hangoutLink": "https://meet.google.com/vna-fyip-xoo",
        "conferenceData": {
            "createRequest": {
                "requestId": "f81a139ceb9b4836a7b887f4ef390e05",
                "conferenceSolutionKey": {
                    "type": "hangoutsMeet"
                },
                "status": {
                    "statusCode": "success"
                }
            },
            "entryPoints": [
                {
                    "entryPointType": "video",
                    "uri": "https://meet.google.com/vna-fyip-xoo",
                    "label": "meet.google.com/vna-fyip-xoo"
                },
                {
                    "entryPointType": "more",
                    "uri": "https://tel.meet/vna-fyip-xoo?pin=7251248266072",
                    "pin": "7251248266072"
                },
                {
                    "regionCode": "US",
                    "entryPointType": "phone",
                    "uri": "tel:+1-929-282-0909",
                    "label": "+1 929-282-0909",
                    "pin": "929481679"
                }
            ],
            "conferenceSolution": {
                "key": {
                    "type": "hangoutsMeet"
                },
                "name": "Google Meet",
                "iconUri": "https://fonts.gstatic.com/s/i/productlogos/meet_2020q4/v6/web-512dp/logo_meet_2020q4_color_2x_web_512dp.png"
            },
            "conferenceId": "vna-fyip-xoo",
            "signature": "AGkP/s0dIggK2afvE5Q5nWNqG946"
        },
        "reminders": {
            "useDefault": false,
            "overrides": [
                {
                    "method": "email",
                    "minutes": 1440
                },
                {
                    "method": "popup",
                    "minutes": 10
                }
            ]
        }
    },
    {
        "kind": "calendar#event",
        "etag": "\"3215749048320000\"",
        "id": "vd2amedfjhahu8855n2ld6ec0s",
        "status": "confirmed",
        "htmlLink": "https://www.google.com/calendar/event?eid=dmQyYW1lZGZqaGFodTg4NTVuMmxkNmVjMHMgY19ja2JpOTg5bzJ1anRjdnR1bW1jbTc1cWpxb0Bn",
        "created": "2020-12-13T08:46:46.000Z",
        "updated": "2020-12-13T15:48:44.187Z",
        "summary": "Javascript",
        "description": "Javascript for Beginners",
        "creator": {
            "email": "jmohale@student.wethinkcode.co.za"
        },
        "organizer": {
            "email": "c_ckbi989o2ujtcvtummcm75qjqo@group.calendar.google.com",
            "displayName": "Fake code clinic",
            "self": true
        },
        "start": {
            "dateTime": "2020-12-19T13:30:00+02:00",
            "timeZone": "Africa/Johannesburg"
        },
        "end": {
            "dateTime": "2020-12-19T14:00:00+02:00",
            "timeZone": "Africa/Johannesburg"
        },
        "iCalUID": "vd2amedfjhahu8855n2ld6ec0s@google.com",
        "sequence": 0,
        "attendees": [
            {
                "email": "jmohale@student.wethinkcode.co.za",
                "responseStatus": "accepted"
            }
        ],
        "hangoutLink": "https://meet.google.com/stn-hkyp-yrr",
        "conferenceData": {
            "createRequest": {
                "requestId": "f81a139ceb9b4836a7b887f4ef390e05",
                "conferenceSolutionKey": {
                    "type": "hangoutsMeet"
                },
                "status": {
                    "statusCode": "success"
                }
            },
            "entryPoints": [
                {
                    "entryPointType": "video",
                    "uri": "https://meet.google.com/stn-hkyp-yrr",
                    "label": "meet.google.com/stn-hkyp-yrr"
                },
                {
                    "entryPointType": "more",
                    "uri": "https://tel.meet/stn-hkyp-yrr?pin=5010029899284",
                    "pin": "5010029899284"
                },
                {
                    "regionCode": "US",
                    "entryPointType": "phone",
                    "uri": "tel:+1-929-276-0318",
                    "label": "+1 929-276-0318",
                    "pin": "452109662"
                }
            ],
            "conferenceSolution": {
                "key": {
                    "type": "hangoutsMeet"
                },
                "name": "Google Meet",
                "iconUri": "https://fonts.gstatic.com/s/i/productlogos/meet_2020q4/v6/web-512dp/logo_meet_2020q4_color_2x_web_512dp.png"
            },
            "conferenceId": "stn-hkyp-yrr",
            "signature": "AGkP/s0Dxbm7KePoaPHl9BwFK1EG"
        },
        "reminders": {
            "useDefault": false,
            "overrides": [
                {
                    "method": "email",
                    "minutes": 1440
                },
                {
                    "method": "popup",
                    "minutes": 10
                }
            ]
        }
    },
    {
        "kind": "calendar#event",
        "etag": "\"3215793933606000\"",
        "id": "t3i19pf81o49pfe63v7sps1p6c",
        "status": "confirmed",
        "htmlLink": "https://www.google.com/calendar/event?eid=dDNpMTlwZjgxbzQ5cGZlNjN2N3NwczFwNmMgY19ja2JpOTg5bzJ1anRjdnR1bW1jbTc1cWpxb0Bn",
        "created": "2020-12-12T12:13:19.000Z",
        "updated": "2020-12-13T22:02:46.833Z",
        "summary": "Java",
        "description": "Check",
        "creator": {
            "email": "jmohale@student.wethinkcode.co.za"
        },
        "organizer": {
            "email": "c_ckbi989o2ujtcvtummcm75qjqo@group.calendar.google.com",
            "displayName": "Fake code clinic",
            "self": true
        },
        "start": {
            "dateTime": "2020-12-15T15:00:00+02:00",
            "timeZone": "Africa/Johannesburg"
        },
        "end": {
            "dateTime": "2020-12-15T15:30:00+02:00",
            "timeZone": "Africa/Johannesburg"
        },
        "iCalUID": "t3i19pf81o49pfe63v7sps1p6c@google.com",
        "sequence": 0,
        "attendees": [
            {
                "email": "jmohale@student.wethinkcode.co.za",
                "responseStatus": "accepted"
            }
        ],
        "hangoutLink": "https://meet.google.com/ygh-ybso-zct",
        "conferenceData": {
            "createRequest": {
                "requestId": "0b9af6d87b4e4474be04daba236aa80d",
                "conferenceSolutionKey": {
                    "type": "hangoutsMeet"
                },
                "status": {
                    "statusCode": "success"
                }
            },
            "entryPoints": [
                {
                    "entryPointType": "video",
                    "uri": "https://meet.google.com/ygh-ybso-zct",
                    "label": "meet.google.com/ygh-ybso-zct"
                },
                {
                    "entryPointType": "more",
                    "uri": "https://tel.meet/ygh-ybso-zct?pin=5242997271048",
                    "pin": "5242997271048"
                },
                {
                    "regionCode": "US",
                    "entryPointType": "phone",
                    "uri": "tel:+1-413-853-0349",
                    "label": "+1 413-853-0349",
                    "pin": "339877116"
                }
            ],
            "conferenceSolution": {
                "key": {
                    "type": "hangoutsMeet"
                },
                "name": "Google Meet",
                "iconUri": "https://fonts.gstatic.com/s/i/productlogos/meet_2020q4/v6/web-512dp/logo_meet_2020q4_color_2x_web_512dp.png"
            },
            "conferenceId": "ygh-ybso-zct",
            "signature": "AGkP/s3j/TEmJTMmnmKX5iCC5RjF"
        },
        "reminders": {
            "useDefault": false,
            "overrides": [
                {
                    "method": "email",
                    "minutes": 1440
                },
                {
                    "method": "popup",
                    "minutes": 10
                }
            ]
        }
    },
    {
        "kind": "calendar#event",
        "etag": "\"3215867369977000\"",
        "id": "k64930ndv380erqebuki5eauo8",
        "status": "confirmed",
        "htmlLink": "https://www.google.com/calendar/event?eid=azY0OTMwbmR2MzgwZXJxZWJ1a2k1ZWF1bzggY19ja2JpOTg5bzJ1anRjdnR1bW1jbTc1cWpxb0Bn",
        "created": "2020-12-14T08:14:44.000Z",
        "updated": "2020-12-14T08:14:45.017Z",
        "summary": "C++",
        "description": "Intro to C++.",
        "creator": {
            "email": "smabitse@student.wethinkcode.co.za"
        },
        "organizer": {
            "email": "c_ckbi989o2ujtcvtummcm75qjqo@group.calendar.google.com",
            "displayName": "Fake code clinic",
            "self": true
        },
        "start": {
            "dateTime": "2020-12-17T13:30:00+02:00",
            "timeZone": "Africa/Johannesburg"
        },
        "end": {
            "dateTime": "2020-12-17T14:00:00+02:00",
            "timeZone": "Africa/Johannesburg"
        },
        "iCalUID": "k64930ndv380erqebuki5eauo8@google.com",
        "sequence": 0,
        "attendees": [
            {
                "email": "smabitse@student.wethinkcode.co.za",
                "responseStatus": "accepted"
            }
        ],
        "hangoutLink": "https://meet.google.com/vez-szhm-qdp",
        "conferenceData": {
            "createRequest": {
                "requestId": "9cc247111e9e427d9fef7096e863fa99",
                "conferenceSolutionKey": {
                    "type": "hangoutsMeet"
                },
                "status": {
                    "statusCode": "success"
                }
            },
            "entryPoints": [
                {
                    "entryPointType": "video",
                    "uri": "https://meet.google.com/vez-szhm-qdp",
                    "label": "meet.google.com/vez-szhm-qdp"
                },
                {
                    "entryPointType": "more",
                    "uri": "https://tel.meet/vez-szhm-qdp?pin=9883895031405",
                    "pin": "9883895031405"
                },
                {
                    "regionCode": "ZA",
                    "entryPointType": "phone",
                    "uri": "tel:+27-10-823-0807",
                    "label": "+27 10 823 0807",
                    "pin": "452632803"
                }
            ],
            "conferenceSolution": {
                "key": {
                    "type": "hangoutsMeet"
                },
                "name": "Google Meet",
                "iconUri": "https://fonts.gstatic.com/s/i/productlogos/meet_2020q4/v6/web-512dp/logo_meet_2020q4_color_2x_web_512dp.png"
            },
            "conferenceId": "vez-szhm-qdp",
            "signature": "AGkP/s2Dr9Ixz8JG3JlwkZlv0xlh"
        },
        "reminders": {
            "useDefault": false,
            "overrides": [
                {
                    "method": "email",
                    "minutes": 1440
                },
                {
                    "method": "popup",
                    "minutes": 10
                }
            ]
        }
    },
    {
        "kind": "calendar#event",
        "etag": "\"3215867371159000\"",
        "id": "ji4f7hjpuplppap157bqadjmmo",
        "status": "confirmed",
        "htmlLink": "https://www.google.com/calendar/event?eid=amk0ZjdoanB1cGxwcGFwMTU3YnFhZGptbW8gY19ja2JpOTg5bzJ1anRjdnR1bW1jbTc1cWpxb0Bn",
        "created": "2020-12-14T08:14:45.000Z",
        "updated": "2020-12-14T08:14:45.605Z",
        "summary": "C++",
        "description": "Intro to C++.",
        "creator": {
            "email": "smabitse@student.wethinkcode.co.za"
        },
        "organizer": {
            "email": "c_ckbi989o2ujtcvtummcm75qjqo@group.calendar.google.com",
            "displayName": "Fake code clinic",
            "self": true
        },
        "start": {
            "dateTime": "2020-12-17T14:00:00+02:00",
            "timeZone": "Africa/Johannesburg"
        },
        "end": {
            "dateTime": "2020-12-17T14:30:00+02:00",
            "timeZone": "Africa/Johannesburg"
        },
        "iCalUID": "ji4f7hjpuplppap157bqadjmmo@google.com",
        "sequence": 0,
        "attendees": [
            {
                "email": "smabitse@student.wethinkcode.co.za",
                "responseStatus": "accepted"
            }
        ],
        "hangoutLink": "https://meet.google.com/oav-rtsr-duz",
        "conferenceData": {
            "createRequest": {
                "requestId": "9cc247111e9e427d9fef7096e863fa99",
                "conferenceSolutionKey": {
                    "type": "hangoutsMeet"
                },
                "status": {
                    "statusCode": "success"
                }
            },
            "entryPoints": [
                {
                    "entryPointType": "video",
                    "uri": "https://meet.google.com/oav-rtsr-duz",
                    "label": "meet.google.com/oav-rtsr-duz"
                },
                {
                    "entryPointType": "more",
                    "uri": "https://tel.meet/oav-rtsr-duz?pin=3933532454240",
                    "pin": "3933532454240"
                },
                {
                    "regionCode": "ZA",
                    "entryPointType": "phone",
                    "uri": "tel:+27-10-823-1251",
                    "label": "+27 10 823 1251",
                    "pin": "370121416"
                }
            ],
            "conferenceSolution": {
                "key": {
                    "type": "hangoutsMeet"
                },
                "name": "Google Meet",
                "iconUri": "https://fonts.gstatic.com/s/i/productlogos/meet_2020q4/v6/web-512dp/logo_meet_2020q4_color_2x_web_512dp.png"
            },
            "conferenceId": "oav-rtsr-duz",
            "signature": "AGkP/s0jnZ9Kw3/od5wguC2bZhTp"
        },
        "reminders": {
            "useDefault": false,
            "overrides": [
                {
                    "method": "email",
                    "minutes": 1440
                },
                {
                    "method": "popup",
                    "minutes": 10
                }
            ]
        }
    },
    {
        "kind": "calendar#event",
        "etag": "\"3215867372314000\"",
        "id": "8gijirlp0oftqqj4v3cll2khko",
        "status": "confirmed",
        "htmlLink": "https://www.google.com/calendar/event?eid=OGdpamlybHAwb2Z0cXFqNHYzY2xsMmtoa28gY19ja2JpOTg5bzJ1anRjdnR1bW1jbTc1cWpxb0Bn",
        "created": "2020-12-14T08:14:46.000Z",
        "updated": "2020-12-14T08:14:46.186Z",
        "summary": "C++",
        "description": "Intro to C++.",
        "creator": {
            "email": "smabitse@student.wethinkcode.co.za"
        },
        "organizer": {
            "email": "c_ckbi989o2ujtcvtummcm75qjqo@group.calendar.google.com",
            "displayName": "Fake code clinic",
            "self": true
        },
        "start": {
            "dateTime": "2020-12-17T14:30:00+02:00",
            "timeZone": "Africa/Johannesburg"
        },
        "end": {
            "dateTime": "2020-12-17T15:00:00+02:00",
            "timeZone": "Africa/Johannesburg"
        },
        "iCalUID": "8gijirlp0oftqqj4v3cll2khko@google.com",
        "sequence": 0,
        "attendees": [
            {
                "email": "smabitse@student.wethinkcode.co.za",
                "responseStatus": "accepted"
            }
        ],
        "hangoutLink": "https://meet.google.com/eez-erqe-nrc",
        "conferenceData": {
            "createRequest": {
                "requestId": "9cc247111e9e427d9fef7096e863fa99",
                "conferenceSolutionKey": {
                    "type": "hangoutsMeet"
                },
                "status": {
                    "statusCode": "success"
                }
            },
            "entryPoints": [
                {
                    "entryPointType": "video",
                    "uri": "https://meet.google.com/eez-erqe-nrc",
                    "label": "meet.google.com/eez-erqe-nrc"
                },
                {
                    "entryPointType": "more",
                    "uri": "https://tel.meet/eez-erqe-nrc?pin=9270752398327",
                    "pin": "9270752398327"
                },
                {
                    "regionCode": "ZA",
                    "entryPointType": "phone",
                    "uri": "tel:+27-10-823-0776",
                    "label": "+27 10 823 0776",
                    "pin": "317095449"
                }
            ],
            "conferenceSolution": {
                "key": {
                    "type": "hangoutsMeet"
                },
                "name": "Google Meet",
                "iconUri": "https://fonts.gstatic.com/s/i/productlogos/meet_2020q4/v6/web-512dp/logo_meet_2020q4_color_2x_web_512dp.png"
            },
            "conferenceId": "eez-erqe-nrc",
            "signature": "AGkP/s0qeA5ZyTgcbxYRgt3xTB86"
        },
        "reminders": {
            "useDefault": false,
            "overrides": [
                {
                    "method": "email",
                    "minutes": 1440
                },
                {
                    "method": "popup",
                    "minutes": 10
                }
            ]
        }
    },
    {
        "kind": "calendar#event",
        "etag": "\"3215798923405000\"",
        "id": "48tojkqsionqkl6llh6035njro",
        "status": "confirmed",
        "htmlLink": "https://www.google.com/calendar/event?eid=NDh0b2prcXNpb25xa2w2bGxoNjAzNW5qcm8gY19ja2JpOTg5bzJ1anRjdnR1bW1jbTc1cWpxb0Bn",
        "created": "2020-12-13T08:46:48.000Z",
        "updated": "2020-12-14T08:17:18.586Z",
        "summary": "Javascript",
        "description": "Javascript for Beginners",
        "creator": {
            "email": "jmohale@student.wethinkcode.co.za"
        },
        "organizer": {
            "email": "c_ckbi989o2ujtcvtummcm75qjqo@group.calendar.google.com",
            "displayName": "Fake code clinic",
            "self": true
        },
        "start": {
            "dateTime": "2020-12-19T14:00:00+02:00",
            "timeZone": "Africa/Johannesburg"
        },
        "end": {
            "dateTime": "2020-12-19T14:30:00+02:00",
            "timeZone": "Africa/Johannesburg"
        },
        "iCalUID": "48tojkqsionqkl6llh6035njro@google.com",
        "sequence": 0,
        "attendees": [
            {
                "email": "jmohale@student.wethinkcode.co.za",
                "responseStatus": "accepted"
            },
            {
                "email": "smabitse@student.wethinkcode.co.za",
                "responseStatus": "accepted"
            }
        ],
        "hangoutLink": "https://meet.google.com/bgw-ovpr-cff",
        "conferenceData": {
            "createRequest": {
                "requestId": "f81a139ceb9b4836a7b887f4ef390e05",
                "conferenceSolutionKey": {
                    "type": "hangoutsMeet"
                },
                "status": {
                    "statusCode": "success"
                }
            },
            "entryPoints": [
                {
                    "entryPointType": "video",
                    "uri": "https://meet.google.com/bgw-ovpr-cff",
                    "label": "meet.google.com/bgw-ovpr-cff"
                },
                {
                    "entryPointType": "more",
                    "uri": "https://tel.meet/bgw-ovpr-cff?pin=1975127712480",
                    "pin": "1975127712480"
                },
                {
                    "regionCode": "US",
                    "entryPointType": "phone",
                    "uri": "tel:+1-631-397-0210",
                    "label": "+1 631-397-0210",
                    "pin": "611806340"
                }
            ],
            "conferenceSolution": {
                "key": {
                    "type": "hangoutsMeet"
                },
                "name": "Google Meet",
                "iconUri": "https://fonts.gstatic.com/s/i/productlogos/meet_2020q4/v6/web-512dp/logo_meet_2020q4_color_2x_web_512dp.png"
            },
            "conferenceId": "bgw-ovpr-cff",
            "signature": "AGkP/s2hUaQdiCa0ofiqItH0wujA"
        },
        "reminders": {
            "useDefault": false,
            "overrides": [
                {
                    "method": "email",
                    "minutes": 1440
                },
                {
                    "method": "popup",
                    "minutes": 10
                }
            ]
        }
    },
    {
        "kind": "calendar#event",
        "etag": "\"3215886755652000\"",
        "id": "4qj0bkub478kq840a2v2kumnqv",
        "status": "confirmed",
        "htmlLink": "https://www.google.com/calendar/event?eid=NHFqMGJrdWI0NzhrcTg0MGEydjJrdW1ucXYgY19ja2JpOTg5bzJ1anRjdnR1bW1jbTc1cWpxb0Bn",
        "created": "2020-12-14T10:56:17.000Z",
        "updated": "2020-12-14T10:56:17.826Z",
        "summary": "cars",
        "creator": {
            "email": "jmohale@student.wethinkcode.co.za"
        },
        "organizer": {
            "email": "c_ckbi989o2ujtcvtummcm75qjqo@group.calendar.google.com",
            "displayName": "Fake code clinic",
            "self": true
        },
        "start": {
            "dateTime": "2020-12-14T14:30:00+02:00"
        },
        "end": {
            "dateTime": "2020-12-14T15:30:00+02:00"
        },
        "iCalUID": "4qj0bkub478kq840a2v2kumnqv@google.com",
        "sequence": 0,
        "reminders": {
            "useDefault": true
        }
    }
]